[
  {
    "destination": "Los Angeles",
    "country": "USA",
    "iata_code": "LAX",
    "price_usd": 3545,
    "cabin": "Business",
    "origin": "TLV",
    "is_deal": false,
    "avg_price_usd": 4498.0
  },
  {
    "destination": "Bali",
    "country": "Indonesia",
    "iata_code": "DPS",
    "price_usd": 3656,
    "cabin": "Business",
    "origin": "TLV",
    "is_deal": false,
    "avg_price_usd": 4498.0
  },
  {
    "destination": "Sydney",
    "country": "Australia",
    "iata_code": "SYD",
    "price_usd": 6293,
    "cabin": "Business",
    "origin": "TLV",
    "is_deal": false,
    "avg_price_usd": 4498.0
  }
]